accelbyte_py_sdk/api/lobby/__init__.py
accelbyte_py_sdk/api/lobby/errors.py
accelbyte_py_sdk/api/lobby/ws_client.py
accelbyte_py_sdk/api/lobby/models/__init__.py
accelbyte_py_sdk/api/lobby/models/handlers_get_users_presence_response.py
accelbyte_py_sdk/api/lobby/models/handlers_user_presence.py
accelbyte_py_sdk/api/lobby/models/log_app_message_declaration.py
accelbyte_py_sdk/api/lobby/models/logconfig_configuration.py
accelbyte_py_sdk/api/lobby/models/model_bulk_friends_request.py
accelbyte_py_sdk/api/lobby/models/model_bulk_friends_response.py
accelbyte_py_sdk/api/lobby/models/model_bulk_users_free_form_notification_request_v1.py
accelbyte_py_sdk/api/lobby/models/model_create_template_request.py
accelbyte_py_sdk/api/lobby/models/model_create_topic_request.py
accelbyte_py_sdk/api/lobby/models/model_create_topic_request_v1.py
accelbyte_py_sdk/api/lobby/models/model_free_form_notification_request.py
accelbyte_py_sdk/api/lobby/models/model_free_form_notification_request_v1.py
accelbyte_py_sdk/api/lobby/models/model_friend_with_platform.py
accelbyte_py_sdk/api/lobby/models/model_friendship_connection.py
accelbyte_py_sdk/api/lobby/models/model_friendship_connection_response.py
accelbyte_py_sdk/api/lobby/models/model_get_all_notification_template_slug_resp.py
accelbyte_py_sdk/api/lobby/models/model_get_all_notification_topics_response.py
accelbyte_py_sdk/api/lobby/models/model_get_friends_response.py
accelbyte_py_sdk/api/lobby/models/model_get_user_friends_response.py
accelbyte_py_sdk/api/lobby/models/model_get_user_incoming_friends_response.py
accelbyte_py_sdk/api/lobby/models/model_get_user_outgoing_friends_response.py
accelbyte_py_sdk/api/lobby/models/model_global_configuration.py
accelbyte_py_sdk/api/lobby/models/model_incoming_friends_with_time_data.py
accelbyte_py_sdk/api/lobby/models/model_list_bulk_user_platforms_response.py
accelbyte_py_sdk/api/lobby/models/model_load_incoming_friends_with_time_response.py
accelbyte_py_sdk_service_lobby-0.23.0.dist-info/METADATA
accelbyte_py_sdk_service_lobby-0.23.0.dist-info/WHEEL
accelbyte_py_sdk_service_lobby-0.23.0.dist-info/top_level.txt
accelbyte_py_sdk_service_lobby-0.23.0.dist-info/RECORD
