Metadata-Version: 2.4
Name: accelbyte-py-sdk-service-lobby
Version: 0.23.0
Summary: AccelByte Python SDK - AccelByte Gaming Services Lobby Server
Requires-Python: >=3.9
Requires-Dist: accelbyte-py-sdk-core
